MANIFEST.in
Makefile
README.rst
bootstrap.py
buildout.cfg
setup.cfg
setup.py
docs/LICENSE.GPL
docs/LICENSE.txt
docs/architecture.png
docs/architecture.svg
src/collective/__init__.py
src/collective.kwetter.egg-info/PKG-INFO
src/collective.kwetter.egg-info/SOURCES.txt
src/collective.kwetter.egg-info/dependency_links.txt
src/collective.kwetter.egg-info/entry_points.txt
src/collective.kwetter.egg-info/namespace_packages.txt
src/collective.kwetter.egg-info/not-zip-safe
src/collective.kwetter.egg-info/paster_plugins.txt
src/collective.kwetter.egg-info/requires.txt
src/collective.kwetter.egg-info/top_level.txt
src/collective/kwetter/__init__.py
src/collective/kwetter/configure.zcml
src/collective/kwetter/m2client.py
src/collective/kwetter/setuphandlers.py
src/collective/kwetter/tests.py
src/collective/kwetter/browser/__init__.py
src/collective/kwetter/browser/avatar.py
src/collective/kwetter/browser/configure.zcml
src/collective/kwetter/browser/helpers.py
src/collective/kwetter/browser/interfaces.py
src/collective/kwetter/browser/kwetter.py
src/collective/kwetter/browser/viewlets.py
src/collective/kwetter/browser/scripts/kwetter.js
src/collective/kwetter/browser/stylesheets/kwetter.css
src/collective/kwetter/browser/templates/timeline.pt
src/collective/kwetter/interfaces/__init__.py
src/collective/kwetter/interfaces/nfgkwetterlayer.py
src/collective/kwetter/profiles/default/collective.kwetter_various.txt
src/collective/kwetter/profiles/default/cssregistry.xml
src/collective/kwetter/profiles/default/jsregistry.xml
src/collective/kwetter/profiles/default/metadata.xml
src/collective/kwetter/profiles/default/skins.xml
src/collective/kwetter/profiles/default/viewlets.xml
src/collective/kwetter/profiles/default/viewlets.xml~