Metadata-Version: 1.0
Name: collective.kwetter
Version: 0.1
Summary: Plone integration for the Kwetter micro-blogging solution
Home-page: http://www.github.com/collective/kwetter
Author: Paul Stevens and Guido Stevens
Author-email: paul (at) nfg (dot) nl
License: GPL
Keywords: Zope Plone microblogging
Platform: UNKNOWN
Classifier: Environment :: Web Environment
Classifier: Framework :: Plone
Classifier: Framework :: Zope2
Classifier: License :: OSI Approved :: GNU General Public License (GPL)
Classifier: Operating System :: OS Independent
Classifier: Programming Language :: Python :: 2.6
